ipmapper/__init__.py
ipmapper/aggregator.py
ipmapper/cli.py
ipmapper/countries.py
ipmapper/data_fetcher.py
ipmapper/lookup.py
ipmapper/output_writer.py
ipmapper/parser.py
ipmapper-1.0.1.dist-info/licenses/LICENSE
ipmapper-1.0.1.dist-info/METADATA
ipmapper-1.0.1.dist-info/WHEEL
ipmapper-1.0.1.dist-info/entry_points.txt
ipmapper-1.0.1.dist-info/top_level.txt
ipmapper-1.0.1.dist-info/RECORD
