Metadata-Version: 2.4
Name: ipmapper
Version: 1.0.1
Summary: Fast offline IP-to-country lookup using RIR data with country names and currency support
Home-page: https://github.com/anxkhn/ipmapper
Author: Anas Khan
Author-email: Anas Khan <anxkhn28@gmail.com>
License: MIT
Project-URL: Homepage, https://github.com/anxkhn/ipmapper
Project-URL: Repository, https://github.com/anxkhn/ipmapper
Project-URL: Issues, https://github.com/anxkhn/ipmapper/issues
Keywords: ip,geolocation,country,currency,rir,offline,radix-tree
Classifier: Development Status :: 5 - Production/Stable
Classifier: Intended Audience :: Developers
Classifier: License :: OSI Approved :: MIT License
Classifier: Operating System :: OS Independent
Classifier: Programming Language :: Python :: 3
Classifier: Programming Language :: Python :: 3.11
Classifier: Programming Language :: Python :: 3.12
Classifier: Topic :: Internet
Classifier: Topic :: Software Development :: Libraries :: Python Modules
Classifier: Topic :: System :: Networking
Requires-Python: >=3.11
License-File: LICENSE
Requires-Dist: requests>=2.31.0
Requires-Dist: click>=8.1.0
Requires-Dist: tqdm>=4.65.0
Dynamic: author
Dynamic: home-page
Dynamic: license-file
Dynamic: requires-python
